app/__init__.py
app/arguments.py
app/elo.py
app/entrypoint.py
app/planner.py
app/taski.py
app/todoist_wrapper.py
app/util.py
taski-0.1.20.data/scripts/taski
taski-0.1.20.dist-info/METADATA
taski-0.1.20.dist-info/RECORD
taski-0.1.20.dist-info/WHEEL
taski-0.1.20.dist-info/top_level.txt
