Metadata-Version: 2.1
Name: taski
Version: 0.1.20
Summary: Taski is a tool to help manage your GTD tasks
Home-page: https://github.com/calio/taski
Author: Jiale Zhi
Author-email: vipcalio@gmail.com
License: MIT
Platform: UNKNOWN
Requires-Dist: todoist-python
Requires-Dist: pytz
Requires-Dist: tzlocal
Requires-Dist: pyyaml
Requires-Dist: coloredlogs
Requires-Dist: npyscreen
Requires-Dist: six
